betterdata/__init__.py
betterdata-23.0.2.dist-info/METADATA
betterdata-23.0.2.dist-info/WHEEL
betterdata-23.0.2.dist-info/RECORD
